pyreqgen/ReqParser.py
pyreqgen/__init__.py
pyreqgen-0.0.4.dist-info/LICENSE
pyreqgen-0.0.4.dist-info/METADATA
pyreqgen-0.0.4.dist-info/WHEEL
pyreqgen-0.0.4.dist-info/top_level.txt
pyreqgen-0.0.4.dist-info/RECORD
